jp_ephys_viz/__init__.py
jp_ephys_viz/jp_ephys_viz_impl.py
jp_ephys_viz/css/bootstrap.min.css
jp_ephys_viz/css/ml-layout.css
jp_ephys_viz/javascript/bundle.js
jp_ephys_viz/javascript/d3.min.js
jp_ephys_viz/javascript/jquery.min.js
jp_ephys_viz-0.6.16.dist-info/METADATA
jp_ephys_viz-0.6.16.dist-info/RECORD
jp_ephys_viz-0.6.16.dist-info/WHEEL
jp_ephys_viz-0.6.16.dist-info/top_level.txt
